README.rst
setup.py
papis_html/__init__.py
papis_html.egg-info/PKG-INFO
papis_html.egg-info/SOURCES.txt
papis_html.egg-info/dependency_links.txt
papis_html.egg-info/entry_points.txt
papis_html.egg-info/requires.txt
papis_html.egg-info/top_level.txt
papis_html/data/index.html
papis_html/data/css/bootstrap.min.css
papis_html/data/js/bibtex_js.js
papis_html/data/js/jquery.min.js